pyconfman/__init__.py
pyconfman/manager.py
pyconfman/plug_cli.py
pyconfman-0.1.0.dist-info/METADATA
pyconfman-0.1.0.dist-info/WHEEL
pyconfman-0.1.0.dist-info/RECORD
