Metadata-Version: 2.1
Name: pyconfman
Version: 0.1.0
Summary: Manage multiple and hierarchical configurations
Author: Giuseppe Di Bona
Author-email: giusedb@gmail.com
Requires-Python: >=3.10,<4.0
Classifier: Programming Language :: Python :: 3
Classifier: Programming Language :: Python :: 3.10
Classifier: Programming Language :: Python :: 3.11
Requires-Dist: click (>=8.1.7,<9.0.0)
Requires-Dist: pyyaml (>=6.0.1,<7.0.0)
